Workbook

Sheet Instructions
A1: Brucellosis Control Cost-Benefit Analysis — Worked Workbook (with formulas)
B3: Purpose
B4: This workbook is the formula version of the brucellosis control cost-benefit exercise: comparing a vaccination program against a test-and-slaughter program for controlling B. melitensis in sheep and goats, over an 8-year period. Every answer cell holds a live Excel formula, so you can click any yellow cell to see how it is calculated, or change an input and watch the results update.
B6: How to use this worksheet
B7: 1. "Cost & Benefit Estimation" sheet — shows where the Year 1–3 costs and benefits come from (vaccination cost, test-and-slaughter cost, avoided human cases, avoided animal losses). Check rows compare each result with the published figure.
B8: 2. "Strategy A - Vaccination" sheet — net value, discount factor, discounted cost and benefit, NPV per year, and cumulative NPV. The gold cell (C3) is the interest rate, 7.74%.
B9: 3. "Strategy B - Test-and-Slaughter" sheet — the same calculations for test-and-slaughter. Each strategy sheet has its own rate cell (C3); change both if you test another rate.
B10: 4. "Summary" sheet — the six comparison metrics link to the strategy sheets, and the two decision answers are chosen by formula (higher BCR for Q1, higher NPV for Q2).
B11: 5. Try it: change the rate, coverage, prevalence or a unit cost and see whether the decisions change.
B13: Colour guide
B14: Blue cell — given data. These are the numbers you need; do not edit them.
B15: Gold cell — key assumption (the interest rate). Already set for you.
B16: Yellow cell — calculated answer. Contains a formula; click it to see how it works.
... B26: Hadzovic, D., Fejzic, N., Seric-Haracic, S., van Asseldonk, M., & Bergevoet, R.H.M. (2025). Cost-benefit analysis of the small ruminants vaccination program against brucellosis (B. melitensis) in Bosnia and Herzegovina. Acta Veterinaria Eurasia, 51, 0082.

Sheet Cost & Benefit Estimation
A1: Before You Start - Cost & Benefit Estimation (Years 1-3)
A2: Shows where the Year 1-3 figures in the Strategy sheets come from. Change any blue input and every yellow cell recalculates.
C3: Given data | D3: Calculated
A5: 1. GIVEN INPUTS
A6: Item | B6: Unit | C6: Value | F6: Hint / source
A7: Population
A8: Sheep population | B8: head | C8: 830000
A9: Goat population | B9: head | C9: 53000
A10: Vaccination program - per-animal costs
A11: Vaccine cost per animal | B11: EUR/head | C11: 0.135
A12: Veterinary / administration cost per animal | B12: EUR/head | C12: 1.55
A13: Other cost per animal | B13: EUR/head | C13: 0.1
A14: Share of population sampled & tested alongside vaccination | B14: % | C14: 0.05
A15: Sampling & testing (both strategies)
A16: Sampling cost per animal tested | B16: EUR/head | C16: 2.55
A17: Testing cost per animal tested | B17: EUR/head | C17: 2.55
A18: Test-and-slaughter
A19: Share of population sampled, tested & culled each year | B19: % | C19: 0.5
A20: Replacement cost per culled animal | B20: EUR/head | C20: 120
A21: Destruction cost per culled animal | B21: EUR/head | C21: 10
A22: Prevalence in Year 1 | B22: % | C22: 0.045 | F22: From the epidemiological model.
A23: Annual fall in prevalence under test-and-slaughter | B23: % | C23: 0.375 | F23: Prevalence each year = previous year x (1 - this rate).
A24: Human case costs
A25: Income loss due to sick leave | B25: EUR/case | C25: 700
A26: Hospitalization | B26: EUR/case | C26: 450
A27: Treatment / medication | B27: EUR/case | C27: 500
A28: Other family costs | B28: EUR/case | C28: 300
A29: Animal production losses
A30: Reduction in reproduction from infection | B30: % | C30: 0.322
A31: Reduction in milk yield from infection | B31: % | C31: 0.15
A32: Reproduction rate - sheep | B32: lambs/ewe/yr | C32: 1.2
A33: Reproduction rate - goats | B33: kids/doe/yr | C33: 1.5
A34: Price per lamb | B34: EUR/head | C34: 80
A35: Price per kid | B35: EUR/head | C35: 90
A36: Milk yield - sheep | B36: L/ewe/yr | C36: 60
A37: Milk yield - goats | B37: L/doe/yr | C37: 115
A38: Milk price - sheep | B38: EUR/L | C38: 0.609
A39: Milk price - goats | B39: EUR/L | C39: 1.307
A41: 2. COST ESTIMATION - VACCINATION PROGRAM
A42: Item | B42: Unit | C42: Year 1 | D42: Year 2 | E42: Year 3 | F42: Hint / source
A43: Vaccination coverage | B43: % | C43: 0.833 | D43: 0.202 | E43: 0.202 | F43: 83.3% in Year 1 (first mass campaign), 20.2% from Year 2 onward.
A44: Vaccination cost - sheep | B44: EUR | C44: =$C$8*C43*($C$11+$C$12+$C$13)+$C$8*$C$14*($C$16+$C$17) -> 1445781.1 | D44: =$C$8*D43*($C$11+$C$12+$C$13)+$C$8*$C$14*($C$16+$C$17) -> 510923.1 | E44: =$C$8*E43*($C$11+$C$12+$C$13)+$C$8*$C$14*($C$16+$C$17) -> 510923.1 | F44: Population x coverage x (vaccine + vet + other) + population x tested share x (sampling + testing).
A45: Vaccination cost - goats | B45: EUR | C45: =$C$9*C43*($C$11+$C$12+$C$13)+$C$9*$C$14*($C$16+$C$17) -> 92320.965 | D45: =$C$9*D43*($C$11+$C$12+$C$13)+$C$9*$C$14*($C$16+$C$17) -> 32625.21 | E45: =$C$9*E43*($C$11+$C$12+$C$13)+$C$9*$C$14*($C$16+$C$17) -> 32625.21 | F45: Same formula, goat population.
A46: Total vaccination costs | B46: EUR | C46: =C44+C45 -> 1538102.1 | D46: =D44+D45 -> 543548.31 | E46: =E44+E45 -> 543548.31 | F46: Sheep + goats.
A47: Awareness campaign | B47: EUR | C47: 30000 | D47: 30000 | E47: 15000
A48: Training | B48: EUR | C48: 40000 | D48: 40000 | E48: 20000
A49: Monitoring | B49: EUR | C49: 24000 | D49: 24000 | E49: 6000
A50: Office running costs | B50: EUR | C50: 10000 | D50: 5000 | E50: 5000
A51: Cold chain set-up & maintenance | B51: EUR | C51: 193500 | D51: 13500 | E51: 13500
A52: Fixed program costs | B52: EUR | C52: =SUM(C47:C51) -> 297500 | D52: =SUM(D47:D51) -> 112500 | E52: =SUM(E47:E51) -> 59500 | F52: Sum of the five fixed-cost rows above.
A53: Total annual cost (calculated) | B53: EUR | C53: =C46+C52 -> 1835602.1 | D53: =D46+D52 -> 656048.31 | E53: =E46+E52 -> 603048.31 | F53: Total vaccination costs + fixed program costs.
A54: Total annual cost (given, Strategy A sheet) | B54: EUR | C54: ='Strategy A - Vaccination'!C9 -> 1835602 | D54: ='Strategy A - Vaccination'!D9 -> 656048 | E54: ='Strategy A - Vaccination'!E9 -> 603048 | F54: Linked from the Strategy A sheet.
A55: Check: calculated - given | B55: EUR | C55: =C53-C54 -> 0.115 | D55: =D53-D54 -> 0.31 | E55: =E53-E54 -> 0.31 | F55: Within +/-1 EUR (published figures are rounded).
A57: 3. COST ESTIMATION - TEST-AND-SLAUGHTER
A58: Item | B58: Unit | C58: Year 1 | D58: Year 2 | E58: Year 3 | F58: Hint / source
A59: Prevalence | B59: % | C59: =$C$22 -> 0.045 | D59: =C59*(1-$C$23) -> 0.028125 | E59: =D59*(1-$C$23) -> 0.017578125 | F59: Year 1 from inputs; then previous year x (1 - annual fall). Gives 4.50%, 2.81%, 1.76%.
A60: Test-and-slaughter cost - sheep | B60: EUR | C60: =$C$8*$C$19*($C$16+$C$17)+$C$8*$C$19*C59*($C$20+$C$21) -> 4544250 | D60: =$C$8*$C$19*($C$16+$C$17)+$C$8*$C$19*D59*($C$20+$C$21) -> 3633843.8 | E60: =$C$8*$C$19*($C$16+$C$17)+$C$8*$C$19*E59*($C$20+$C$21) -> 3064839.8 | F60: Population x tested share x (sampling + testing) + population x tested share x prevalence x (replacement + destruction).
A61: Test-and-slaughter cost - goats | B61: EUR | C61: =$C$9*$C$19*($C$16+$C$17)+$C$9*$C$19*C59*($C$20+$C$21) -> 290175 | D61: =$C$9*$C$19*($C$16+$C$17)+$C$9*$C$19*D59*($C$20+$C$21) -> 232040.62 | E61: =$C$9*$C$19*($C$16+$C$17)+$C$9*$C$19*E59*($C$20+$C$21) -> 195706.64 | F61: Same formula, goat population.
A62: Total annual cost (calculated) | B62: EUR | C62: =C60+C61 -> 4834425 | D62: =D60+D61 -> 3865884.4 | E62: =E60+E61 -> 3260546.5 | F62: Sheep + goats.
A63: Total annual cost (given, Strategy B sheet) | B63: EUR | C63: ='Strategy B - Test-and-Slaughter'!C9 -> 4834425 | D63: ='Strategy B - Test-and-Slaughter'!D9 -> 3865884 | E63: ='Strategy B - Test-and-Slaughter'!E9 -> 3260546 | F63: Linked from the Strategy B sheet.
A64: Check: calculated - given | B64: EUR | C64: =C62-C63 -> 0 | D64: =D62-D63 -> 0.375 | E64: =E62-E63 -> 0.484375 | F64: Within +/-1 EUR (published figures are rounded).
A66: 4. BENEFIT ESTIMATION - AVOIDED HUMAN CASES (same for both strategies)
A67: Item | B67: Unit | C67: Year 1 | D67: Year 2 | E67: Year 3 | F67: Hint / source
A68: Avoided human cases | B68: cases | C68: 0 | D68: 403 | E68: 743 | F68: From the model, vs. the rising trend under no control.
A69: Cost per human case | B69: EUR/case | C69: =$C$25+$C$26+$C$27+$C$28 -> 1950 | D69: =$C$25+$C$26+$C$27+$C$28 -> 1950 | E69: =$C$25+$C$26+$C$27+$C$28 -> 1950 | F69: Income loss + hospitalization + treatment + other family costs.
A70: Avoided human-case benefit (calculated) | B70: EUR | C70: =C68*C69 -> 0 | D70: =D68*D69 -> 785850 | E70: =E68*E69 -> 1448850 | F70: Avoided cases x cost per case.
A71: Avoided human-case benefit (published) | B71: EUR | C71: 0 | D71: 785012 | E71: 1448346 | F71: Hadzovic et al. (2025).
A72: Check: calculated - published | B72: EUR | C72: =C70-C71 -> 0 | D72: =D70-D71 -> 838 | E72: =E70-E71 -> 504 | F72: Small gap: the model's case counts are not whole numbers (about 402.6 and 742.7).
A74: 5. BENEFIT ESTIMATION - AVOIDED ANIMAL LOSSES
A75: Item | B75: Unit | C75: Year 1 | D75: Year 2 | E75: Year 3 | F75: Hint / source
A76: Fall in prevalence (delta P) | B76: % | C76: 0 | D76: 0.019 | E76: 0.04 | F76: From the epidemiological model, rounded to 1.9% and 4% for hand calculation.
A77: Avoided abortion value - sheep | B77: EUR | C77: =C76*$C$8*$C$30*$C$32*$C$34 -> 0 | D77: =D76*$C$8*$C$30*$C$32*$C$34 -> 487482.24 | E77: =E76*$C$8*$C$30*$C$32*$C$34 -> 1026278.4 | F77: delta P x sheep population x reduction in reproduction x reproduction rate x price per lamb.
A78: Avoided milk-loss value - sheep | B78: EUR | C78: =C76*$C$8*$C$31*$C$36*$C$38 -> 0 | D78: =D76*$C$8*$C$31*$C$36*$C$38 -> 86435.37 | E78: =E76*$C$8*$C$31*$C$36*$C$38 -> 181969.2 | F78: delta P x sheep population x reduction in milk yield x milk yield x milk price.
A79: Avoided abortion value - goats | B79: EUR | C79: =C76*$C$9*$C$30*$C$33*$C$35 -> 0 | D79: =D76*$C$9*$C$30*$C$33*$C$35 -> 43774.29 | E79: =E76*$C$9*$C$30*$C$33*$C$35 -> 92156.4 | F79: delta P x goat population x reduction in reproduction x reproduction rate x price per kid.
A80: Avoided milk-loss value - goats | B80: EUR | C80: =C76*$C$9*$C$31*$C$37*$C$39 -> 0 | D80: =D76*$C$9*$C$31*$C$37*$C$39 -> 22703.57 | E80: =E76*$C$9*$C$31*$C$37*$C$39 -> 47796.99 | F80: delta P x goat population x reduction in milk yield x milk yield x milk price.
A81: Total avoided animal-loss benefit (calculated) | B81: EUR | C81: =SUM(C77:C80) -> 0 | D81: =SUM(D77:D80) -> 640395.47 | E81: =SUM(E77:E80) -> 1348201 | F81: Sum of the four values above.
A82: Avoided animal-loss benefit (published) | B82: EUR | C82: 0 | D82: 651741 | E82: 1357577 | F82: Hadzovic et al. (2025).
A83: Check: calculated - published | B83: EUR | C83: =C81-C82 -> 0 | D83: =D81-D82 -> -11345.53 | E83: =E81-E82 -> -9376.01 | F83: Slightly below published because delta P is rounded (about 1.7% lower in Year 2, 0.7% in Year 3).

Sheet Strategy A - Vaccination
A1: Strategy A - Vaccination
A3: Interest rate used for discounting (r): | C3: 0.0774
B5: Given data | E5: Key assumption | H5: Calculated (formula)
A7: Item | B7: Unit | C7: Year 1 | D7: Year 2 | E7: Year 3 | F7: Year 4 | G7: Year 5 | H7: Year 6 | I7: Year 7 | J7: Year 8 | K7: Total | L7: Hint (how to calculate)
A8: 1. GIVEN DATA (EUR)
A9: Total annual cost | B9: EUR/yr | C9: 1835602 | D9: 656048 | E9: 603048 | F9: 603048 | G9: 603048 | H9: 603048 | I9: 603048 | J9: 603049 | K9: =SUM(C9:J9) -> 6109939
A10: Total annual benefit | B10: EUR/yr | C10: 823348 | D10: 2260101 | E10: 3629271 | F10: 5008894 | G10: 6470455 | H10: 8084010 | I10: 9922737 | J10: 12067258 | K10: =SUM(C10:J10) -> 48266074
A12: 2. NET VALUE & DISCOUNTED CASH FLOW (EUR)
A13: Net value (undiscounted) | B13: EUR/yr | C13: =C10-C9 -> -1012254 | D13: =D10-D9 -> 1604053 | E13: =E10-E9 -> 3026223 | F13: =F10-F9 -> 4405846 | G13: =G10-G9 -> 5867407 | H13: =H10-H9 -> 7480962 | I13: =I10-I9 -> 9319689 | J13: =J10-J9 -> 11464209 | K13: =SUM(C13:J13) -> 42156135 | L13: Total annual benefit − total annual cost.
A14: Discount factor (r = 7.74%) | B14: — | C14: =1/(1+$C$3)^0 -> 1 | D14: =1/(1+$C$3)^1 -> 0.92816039 | E14: =1/(1+$C$3)^2 -> 0.8614817 | F14: =1/(1+$C$3)^3 -> 0.79959319 | G14: =1/(1+$C$3)^4 -> 0.74215072 | H14: =1/(1+$C$3)^5 -> 0.6888349 | I14: =1/(1+$C$3)^6 -> 0.63934927 | J14: =1/(1+$C$3)^7 -> 0.59341866 | K14: — | L14: 1 ÷ (1 + r)^t, using the rate in 'Strategy A - Vaccination'!$C$3. t = year number − 1. No total for this row.
A15: Discounted cost | B15: EUR/yr | C15: =C9*C14 -> 1835602 | D15: =D9*D14 -> 608917.76 | E15: =E9*E14 -> 519514.82 | F15: =F9*F14 -> 482193.07 | G15: =G9*G14 -> 447552.51 | H15: =H9*H14 -> 415400.51 | I15: =I9*I14 -> 385558.3 | J15: =J9*J14 -> 357860.53 | K15: =SUM(C15:J15) -> 5052599.5 | L15: Total annual cost × discount factor.
A16: Discounted benefit | B16: EUR/yr | C16: =C10*C14 -> 823348 | D16: =D10*D14 -> 2097736.2 | E16: =E10*E14 -> 3126550.6 | F16: =F10*F14 -> 4005077.5 | G16: =G10*G14 -> 4802052.9 | H16: =H10*H14 -> 5568548.2 | I16: =I10*I14 -> 6344094.6 | J16: =J10*J14 -> 7160936.1 | K16: =SUM(C16:J16) -> 33928344 | L16: Total annual benefit × discount factor.
A17: Net present value (per year) | B17: EUR/yr | C17: =C16-C15 -> -1012254 | D17: =D16-D15 -> 1488818.5 | E17: =E16-E15 -> 2607035.7 | F17: =F16-F15 -> 3522884.5 | G17: =G16-G15 -> 4354500.4 | H17: =H16-H15 -> 5153147.7 | I17: =I16-I15 -> 5958536.3 | J17: =J16-J15 -> 6803075.6 | K17: =SUM(C17:J17) -> 28875745 | L17: Discounted benefit − discounted cost.
A18: Cumulative NPV | B18: EUR | C18: =C17 -> -1012254 | D18: =C18+D17 -> 476564.45 | E18: =D18+E17 -> 3083600.2 | F18: =E18+F17 -> 6606484.6 | G18: =F18+G17 -> 10960985 | H18: =G18+H17 -> 16114133 | I18: =H18+I17 -> 22072669 | J18: =I18+J17 -> 28875745 | K18: =J18 -> 28875745 | L18: Running sum of NPV per year. Total should match the final year’s cumulative value.

Sheet Strategy B - Test-and-Slaughter
A1: Strategy B - Test-and-Slaughter
A3: Interest rate used for discounting (r): | C3: 0.0774
B5: Given data | E5: Key assumption | H5: Calculated (formula)
A7: Item | B7: Unit | C7: Year 1 | D7: Year 2 | E7: Year 3 | F7: Year 4 | G7: Year 5 | H7: Year 6 | I7: Year 7 | J7: Year 8 | K7: Total | L7: Hint (how to calculate)
A8: 1. GIVEN DATA (EUR)
A9: Total annual cost | B9: EUR/yr | C9: 4834425 | D9: 3865884 | E9: 3260546 | F9: 2882210 | G9: 2645750 | H9: 2497963 | I9: 2405595 | J9: 2347866 | K9: =SUM(C9:J9) -> 24740239
A10: Total annual benefit | B10: EUR/yr | C10: 823348 | D10: 4283189 | E10: 6985968 | F10: 9734670 | G10: 12614800 | H10: 15834289 | I10: 19588968 | J10: 24082167 | K10: =SUM(C10:J10) -> 93947399
A12: 2. NET VALUE & DISCOUNTED CASH FLOW (EUR)
A13: Net value (undiscounted) | B13: EUR/yr | C13: =C10-C9 -> -4011077 | D13: =D10-D9 -> 417305 | E13: =E10-E9 -> 3725422 | F13: =F10-F9 -> 6852460 | G13: =G10-G9 -> 9969050 | H13: =H10-H9 -> 13336326 | I13: =I10-I9 -> 17183373 | J13: =J10-J9 -> 21734301 | K13: =SUM(C13:J13) -> 69207160 | L13: Total annual benefit − total annual cost.
A14: Discount factor (r = 7.74%) | B14: — | C14: =1/(1+$C$3)^0 -> 1 | D14: =1/(1+$C$3)^1 -> 0.92816039 | E14: =1/(1+$C$3)^2 -> 0.8614817 | F14: =1/(1+$C$3)^3 -> 0.79959319 | G14: =1/(1+$C$3)^4 -> 0.74215072 | H14: =1/(1+$C$3)^5 -> 0.6888349 | I14: =1/(1+$C$3)^6 -> 0.63934927 | J14: =1/(1+$C$3)^7 -> 0.59341866 | K14: — | L14: 1 ÷ (1 + r)^t, using the rate in 'Strategy B - Test-and-Slaughter'!$C$3. t = year number − 1. No total for this row.
A15: Discounted cost | B15: EUR/yr | C15: =C9*C14 -> 4834425 | D15: =D9*D14 -> 3588160.4 | E15: =E9*E14 -> 2808900.7 | F15: =F9*F14 -> 2304595.5 | G15: =G9*G14 -> 1963545.3 | H15: =H9*H14 -> 1720684.1 | I15: =I9*I14 -> 1538015.4 | J15: =J9*J14 -> 1393267.5 | K15: =SUM(C15:J15) -> 20151594 | L15: Total annual cost × discount factor.
A16: Discounted benefit | B16: EUR/yr | C16: =C10*C14 -> 823348 | D16: =D10*D14 -> 3975486.4 | E16: =E10*E14 -> 6018283.6 | F16: =F10*F14 -> 7783775.8 | G16: =G10*G14 -> 9362082.9 | H16: =H10*H14 -> 10907211 | I16: =I10*I14 -> 12524192 | J16: =J10*J14 -> 14290807 | K16: =SUM(C16:J16) -> 65685187 | L16: Total annual benefit × discount factor.
A17: Net present value (per year) | B17: EUR/yr | C17: =C16-C15 -> -4011077 | D17: =D16-D15 -> 387325.97 | E17: =E16-E15 -> 3209382.9 | F17: =F16-F15 -> 5479180.3 | G17: =G16-G15 -> 7398537.7 | H17: =H16-H15 -> 9186526.8 | I17: =I16-I15 -> 10986177 | J17: =J16-J15 -> 12897540 | K17: =SUM(C17:J17) -> 45533594 | L17: Discounted benefit − discounted cost.
A18: Cumulative NPV | B18: EUR | C18: =C17 -> -4011077 | D18: =C18+D17 -> -3623751 | E18: =D18+E17 -> -414368.14 | F18: =E18+F17 -> 5064812.2 | G18: =F18+G17 -> 12463350 | H18: =G18+H17 -> 21649877 | I18: =H18+I17 -> 32636054 | J18: =I18+J17 -> 45533594 | K18: =J18 -> 45533594 | L18: Running sum of NPV per year. Total should match the final year’s cumulative value.

Sheet Summary
A1: Summary: Compare the Two Strategies
C3: Yellow cell = calculated (formula)
A5: Metric | B5: Vaccination | C5: Test-and-Slaughter | D5: Hint
A6: Total cost (undiscounted, 8-yr) | B6: ='Strategy A - Vaccination'!K9 -> 6109939 | C6: ='Strategy B - Test-and-Slaughter'!K9 -> 24740239 | D6: Total column, Total annual cost row on each strategy's sheet.
A7: Total benefit (undiscounted, 8-yr) | B7: ='Strategy A - Vaccination'!K10 -> 48266074 | C7: ='Strategy B - Test-and-Slaughter'!K10 -> 93947399 | D7: Total column, Total annual benefit row on each strategy's sheet.
A8: Total discounted cost | B8: ='Strategy A - Vaccination'!K15 -> 5052599.5 | C8: ='Strategy B - Test-and-Slaughter'!K15 -> 20151594 | D8: Total column, Discounted cost row.
A9: Total discounted benefit | B9: ='Strategy A - Vaccination'!K16 -> 33928344 | C9: ='Strategy B - Test-and-Slaughter'!K16 -> 65685187 | D9: Total column, Discounted benefit row.
A10: Net present value – NPV | B10: ='Strategy A - Vaccination'!K17 -> 28875745 | C10: ='Strategy B - Test-and-Slaughter'!K17 -> 45533594 | D10: Sum of NPV per year (= final cumulative NPV).
A11: Cost-benefit ratio – BCR | B11: =B9/B8 -> 6.7150274 | C11: =C9/C8 -> 3.259553 | D11: Total discounted benefit ÷ total discounted cost.
A13: 3. DECISION
A14: Q1. Limited budget — which strategy offers better value for money? | B14: =IF(B11>C11,"Vaccination","Test-and-Slaughter") -> Vaccination | C14: Picks the strategy with the higher BCR (value per euro spent).
A15: Q2. No budget constraint — which strategy gives the largest NPV? | B15: =IF(B10>C10,"Vaccination","Test-and-Slaughter") -> Test-and-Slaughter | C15: Picks the strategy with the higher total NPV (largest absolute gain).
